Workbook

Sheet 00_Dashboard
B2: Osszes Ido [Auto] | E2: Top Kategoriak – aktualis honap [Auto] | H2: 6 Honapos Trend [Auto]
B3: Osszes Bevetel (HUF) | C3: =SUMIFS('01_Transactions'!L:L,'01_Transactions'!B:B,"Income") -> 0 | E3: =IFERROR('90_Settings'!B2,"") -> 0 | F3: =IFERROR(SUMPRODUCT(('01_Transactions'!F$2:F$5000='90_Settings'!B2)*(YEAR('01_Transactions'!A$2:A$5000)=YEAR(DATE(YEAR(TODAY()),MONTH(TODAY()),1)))*(MONTH('01_Transactions'!A$2:A$5000)=MONTH(DATE(YEAR(TODAY()),MONTH(TODAY()),1)))*'01_Transactions'!L$2:L$5000),0) -> 0 | I3: =TEXT(DATE(YEAR(TODAY()),MONTH(TODAY())+(-5),1),"YYYY-MM") -> 0 | J3: =TEXT(DATE(YEAR(TODAY()),MONTH(TODAY())+(-4),1),"YYYY-MM") -> 0 | K3: =TEXT(DATE(YEAR(TODAY()),MONTH(TODAY())+(-3),1),"YYYY-MM") -> 0 | L3: =TEXT(DATE(YEAR(TODAY()),MONTH(TODAY())+(-2),1),"YYYY-MM") -> 0 | M3: =TEXT(DATE(YEAR(TODAY()),MONTH(TODAY())+(-1),1),"YYYY-MM") -> 0 | N3: =TEXT(DATE(YEAR(TODAY()),MONTH(TODAY()),1),"YYYY-MM") -> 0
B4: Osszes Kiadas (HUF) | C4: =SUMIFS('01_Transactions'!L:L,'01_Transactions'!B:B,"Expense") -> 0 | E4: =IFERROR('90_Settings'!B3,"") -> 0 | F4: =IFERROR(SUMPRODUCT(('01_Transactions'!F$2:F$5000='90_Settings'!B3)*(YEAR('01_Transactions'!A$2:A$5000)=YEAR(DATE(YEAR(TODAY()),MONTH(TODAY()),1)))*(MONTH('01_Transactions'!A$2:A$5000)=MONTH(DATE(YEAR(TODAY()),MONTH(TODAY()),1)))*'01_Transactions'!L$2:L$5000),0) -> 0 | H4: Bevetel | I4: =SUMPRODUCT(('01_Transactions'!B$2:B$5000="Income")*(YEAR('01_Transactions'!A$2:A$5000)=YEAR(DATE(YEAR(TODAY()),MONTH(TODAY())+(-5),1)))*(MONTH('01_Transactions'!A$2:A$5000)=MONTH(DATE(YEAR(TODAY()),MONTH(TODAY())+(-5),1)))*'01_Transactions'!L$2:L$5000) -> 0 | J4: =SUMPRODUCT(('01_Transactions'!B$2:B$5000="Income")*(YEAR('01_Transactions'!A$2:A$5000)=YEAR(DATE(YEAR(TODAY()),MONTH(TODAY())+(-4),1)))*(MONTH('01_Transactions'!A$2:A$5000)=MONTH(DATE(YEAR(TODAY()),MONTH(TODAY())+(-4),1)))*'01_Transactions'!L$2:L$5000) -> 0 | K4: =SUMPRODUCT(('01_Transactions'!B$2:B$5000="Income")*(YEAR('01_Transactions'!A$2:A$5000)=YEAR(DATE(YEAR(TODAY()),MONTH(TODAY())+(-3),1)))*(MONTH('01_Transactions'!A$2:A$5000)=MONTH(DATE(YEAR(TODAY()),MONTH(TODAY())+(-3),1)))*'01_Transactions'!L$2:L$5000) -> 0 | L4: =SUMPRODUCT(('01_Transactions'!B$2:B$5000="Income")*(YEAR('01_Transactions'!A$2:A$5000)=YEAR(DATE(YEAR(TODAY()),MONTH(TODAY())+(-2),1)))*(MONTH('01_Transactions'!A$2:A$5000)=MONTH(DATE(YEAR(TODAY()),MONTH(TODAY())+(-2),1)))*'01_Transactions'!L$2:L$5000) -> 0 | M4: =SUMPRODUCT(('01_Transactions'!B$2:B$5000="Income")*(YEAR('01_Transactions'!A$2:A$5000)=YEAR(DATE(YEAR(TODAY()),MONTH(TODAY())+(-1),1)))*(MONTH('01_Transactions'!A$2:A$5000)=MONTH(DATE(YEAR(TODAY()),MONTH(TODAY())+(-1),1)))*'01_Transactions'!L$2:L$5000) -> 0 | N4: =SUMPRODUCT(('01_Transactions'!B$2:B$5000="Income")*(YEAR('01_Transactions'!A$2:A$5000)=YEAR(DATE(YEAR(TODAY()),MONTH(TODAY()),1)))*(MONTH('01_Transactions'!A$2:A$5000)=MONTH(DATE(YEAR(TODAY()),MONTH(TODAY()),1)))*'01_Transactions'!L$2:L$5000) -> 0
B5: Netto Vagyon (HUF) | C5: =C3-C4 -> 0 | E5: =IFERROR('90_Settings'!B4,"") -> 0 | F5: =IFERROR(SUMPRODUCT(('01_Transactions'!F$2:F$5000='90_Settings'!B4)*(YEAR('01_Transactions'!A$2:A$5000)=YEAR(DATE(YEAR(TODAY()),MONTH(TODAY()),1)))*(MONTH('01_Transactions'!A$2:A$5000)=MONTH(DATE(YEAR(TODAY()),MONTH(TODAY()),1)))*'01_Transactions'!L$2:L$5000),0) -> 0 | H5: Kiadas | I5: =SUMPRODUCT(('01_Transactions'!B$2:B$5000="Expense")*(YEAR('01_Transactions'!A$2:A$5000)=YEAR(DATE(YEAR(TODAY()),MONTH(TODAY())+(-5),1)))*(MONTH('01_Transactions'!A$2:A$5000)=MONTH(DATE(YEAR(TODAY()),MONTH(TODAY())+(-5),1)))*'01_Transactions'!L$2:L$5000) -> 0 | J5: =SUMPRODUCT(('01_Transactions'!B$2:B$5000="Expense")*(YEAR('01_Transactions'!A$2:A$5000)=YEAR(DATE(YEAR(TODAY()),MONTH(TODAY())+(-4),1)))*(MONTH('01_Transactions'!A$2:A$5000)=MONTH(DATE(YEAR(TODAY()),MONTH(TODAY())+(-4),1)))*'01_Transactions'!L$2:L$5000) -> 0 | K5: =SUMPRODUCT(('01_Transactions'!B$2:B$5000="Expense")*(YEAR('01_Transactions'!A$2:A$5000)=YEAR(DATE(YEAR(TODAY()),MONTH(TODAY())+(-3),1)))*(MONTH('01_Transactions'!A$2:A$5000)=MONTH(DATE(YEAR(TODAY()),MONTH(TODAY())+(-3),1)))*'01_Transactions'!L$2:L$5000) -> 0 | L5: =SUMPRODUCT(('01_Transactions'!B$2:B$5000="Expense")*(YEAR('01_Transactions'!A$2:A$5000)=YEAR(DATE(YEAR(TODAY()),MONTH(TODAY())+(-2),1)))*(MONTH('01_Transactions'!A$2:A$5000)=MONTH(DATE(YEAR(TODAY()),MONTH(TODAY())+(-2),1)))*'01_Transactions'!L$2:L$5000) -> 0 | M5: =SUMPRODUCT(('01_Transactions'!B$2:B$5000="Expense")*(YEAR('01_Transactions'!A$2:A$5000)=YEAR(DATE(YEAR(TODAY()),MONTH(TODAY())+(-1),1)))*(MONTH('01_Transactions'!A$2:A$5000)=MONTH(DATE(YEAR(TODAY()),MONTH(TODAY())+(-1),1)))*'01_Transactions'!L$2:L$5000) -> 0 | N5: =SUMPRODUCT(('01_Transactions'!B$2:B$5000="Expense")*(YEAR('01_Transactions'!A$2:A$5000)=YEAR(DATE(YEAR(TODAY()),MONTH(TODAY()),1)))*(MONTH('01_Transactions'!A$2:A$5000)=MONTH(DATE(YEAR(TODAY()),MONTH(TODAY()),1)))*'01_Transactions'!L$2:L$5000) -> 0
E6: =IFERROR('90_Settings'!B5,"") -> 0 | F6: =IFERROR(SUMPRODUCT(('01_Transactions'!F$2:F$5000='90_Settings'!B5)*(YEAR('01_Transactions'!A$2:A$5000)=YEAR(DATE(YEAR(TODAY()),MONTH(TODAY()),1)))*(MONTH('01_Transactions'!A$2:A$5000)=MONTH(DATE(YEAR(TODAY()),MONTH(TODAY()),1)))*'01_Transactions'!L$2:L$5000),0) -> 0 | H6: Cashflow | I6: =SUMPRODUCT(('01_Transactions'!B$2:B$5000="Income")*(YEAR('01_Transactions'!A$2:A$5000)=YEAR(DATE(YEAR(TODAY()),MONTH(TODAY())+(-5),1)))*(MONTH('01_Transactions'!A$2:A$5000)=MONTH(DATE(YEAR(TODAY()),MONTH(TODAY())+(-5),1)))*'01_Transactions'!L$2:L$5000)-SUMPRODUCT(('01_Transactions'!B$2:B$5000="Expense")*(YEAR('01_Transactions'!A$2:A$5000)=YEAR(DATE(YEAR(TODAY()),MONTH(TODAY())+(-5),1)))*(MONTH('01_Transactions'!A$2:A$5000)=MONTH(DATE(YEAR(TODAY()),MONTH(TODAY())+(-5),1)))*'01_Transactions'!L$2:L$5000) -> 0 | J6: =SUMPRODUCT(('01_Transactions'!B$2:B$5000="Income")*(YEAR('01_Transactions'!A$2:A$5000)=YEAR(DATE(YEAR(TODAY()),MONTH(TODAY())+(-4),1)))*(MONTH('01_Transactions'!A$2:A$5000)=MONTH(DATE(YEAR(TODAY()),MONTH(TODAY())+(-4),1)))*'01_Transactions'!L$2:L$5000)-SUMPRODUCT(('01_Transactions'!B$2:B$5000="Expense")*(YEAR('01_Transactions'!A$2:A$5000)=YEAR(DATE(YEAR(TODAY()),MONTH(TODAY())+(-4),1)))*(MONTH('01_Transactions'!A$2:A$5000)=MONTH(DATE(YEAR(TODAY()),MONTH(TODAY())+(-4),1)))*'01_Transactions'!L$2:L$5000) -> 0 | K6: =SUMPRODUCT(('01_Transactions'!B$2:B$5000="Income")*(YEAR('01_Transactions'!A$2:A$5000)=YEAR(DATE(YEAR(TODAY()),MONTH(TODAY())+(-3),1)))*(MONTH('01_Transactions'!A$2:A$5000)=MONTH(DATE(YEAR(TODAY()),MONTH(TODAY())+(-3),1)))*'01_Transactions'!L$2:L$5000)-SUMPRODUCT(('01_Transactions'!B$2:B$5000="Expense")*(YEAR('01_Transactions'!A$2:A$5000)=YEAR(DATE(YEAR(TODAY()),MONTH(TODAY())+(-3),1)))*(MONTH('01_Transactions'!A$2:A$5000)=MONTH(DATE(YEAR(TODAY()),MONTH(TODAY())+(-3),1)))*'01_Transactions'!L$2:L$5000) -> 0 | L6: =SUMPRODUCT(('01_Transactions'!B$2:B$5000="Income")*(YEAR('01_Transactions'!A$2:A$5000)=YEAR(DATE(YEAR(TODAY()),MONTH(TODAY())+(-2),1)))*(MONTH('01_Transactions'!A$2:A$5000)=MONTH(DATE(YEAR(TODAY()),MONTH(TODAY())+(-2),1)))*'01_Transactions'!L$2:L$5000)-SUMPRODUCT(('01_Transactions'!B$2:B$5000="Expense")*(YEAR('01_Transactions'!A$2:A$5000)=YEAR(DATE(YEAR(TODAY()),MONTH(TODAY())+(-2),1)))*(MONTH('01_Transactions'!A$2:A$5000)=MONTH(DATE(YEAR(TODAY()),MONTH(TODAY())+(-2),1)))*'01_Transactions'!L$2:L$5000) -> 0 | M6: =SUMPRODUCT(('01_Transactions'!B$2:B$5000="Income")*(YEAR('01_Transactions'!A$2:A$5000)=YEAR(DATE(YEAR(TODAY()),MONTH(TODAY())+(-1),1)))*(MONTH('01_Transactions'!A$2:A$5000)=MONTH(DATE(YEAR(TODAY()),MONTH(TODAY())+(-1),1)))*'01_Transactions'!L$2:L$5000)-SUMPRODUCT(('01_Transactions'!B$2:B$5000="Expense")*(YEAR('01_Transactions'!A$2:A$5000)=YEAR(DATE(YEAR(TODAY()),MONTH(TODAY())+(-1),1)))*(MONTH('01_Transactions'!A$2:A$5000)=MONTH(DATE(YEAR(TODAY()),MONTH(TODAY())+(-1),1)))*'01_Transactions'!L$2:L$5000) -> 0 | N6: =SUMPRODUCT(('01_Transactions'!B$2:B$5000="Income")*(YEAR('01_Transactions'!A$2:A$5000)=YEAR(DATE(YEAR(TODAY()),MONTH(TODAY()),1)))*(MONTH('01_Transactions'!A$2:A$5000)=MONTH(DATE(YEAR(TODAY()),MONTH(TODAY()),1)))*'01_Transactions'!L$2:L$5000)-SUMPRODUCT(('01_Transactions'!B$2:B$5000="Expense")*(YEAR('01_Transactions'!A$2:A$5000)=YEAR(DATE(YEAR(TODAY()),MONTH(TODAY()),1)))*(MONTH('01_Transactions'!A$2:A$5000)=MONTH(DATE(YEAR(TODAY()),MONTH(TODAY()),1)))*'01_Transactions'!L$2:L$5000) -> 0
B7: Aktualis Honap [Auto] | E7: =IFERROR('90_Settings'!B6,"") -> 0 | F7: =IFERROR(SUMPRODUCT(('01_Transactions'!F$2:F$5000='90_Settings'!B6)*(YEAR('01_Transactions'!A$2:A$5000)=YEAR(DATE(YEAR(TODAY()),MONTH(TODAY()),1)))*(MONTH('01_Transactions'!A$2:A$5000)=MONTH(DATE(YEAR(TODAY()),MONTH(TODAY()),1)))*'01_Transactions'!L$2:L$5000),0) -> 0
B8: Havi Bevetel | C8: =SUMPRODUCT(('01_Transactions'!B$2:B$5000="Income")*(YEAR('01_Transactions'!A$2:A$5000)=YEAR(DATE(YEAR(TODAY()),MONTH(TODAY()),1)))*(MONTH('01_Transactions'!A$2:A$5000)=MONTH(DATE(YEAR(TODAY()),MONTH(TODAY()),1)))*'01_Transactions'!L$2:L$5000) -> 0 | E8: =IFERROR('90_Settings'!B7,"") -> 0 | F8: =IFERROR(SUMPRODUCT(('01_Transactions'!F$2:F$5000='90_Settings'!B7)*(YEAR('01_Transactions'!A$2:A$5000)=YEAR(DATE(YEAR(TODAY()),MONTH(TODAY()),1)))*(MONTH('01_Transactions'!A$2:A$5000)=MONTH(DATE(YEAR(TODAY()),MONTH(TODAY()),1)))*'01_Transactions'!L$2:L$5000),0) -> 0 | H8: Kategoriak – 6 honapos bontasban [Auto]
B9: Havi Kiadas | C9: =SUMPRODUCT(('01_Transactions'!B$2:B$5000="Expense")*(YEAR('01_Transactions'!A$2:A$5000)=YEAR(DATE(YEAR(TODAY()),MONTH(TODAY()),1)))*(MONTH('01_Transactions'!A$2:A$5000)=MONTH(DATE(YEAR(TODAY()),MONTH(TODAY()),1)))*'01_Transactions'!L$2:L$5000) -> 0 | H9: Kategoria | I9: =TEXT(DATE(YEAR(TODAY()),MONTH(TODAY())+(-5),1),"YYYY-MM") -> 0 | J9: =TEXT(DATE(YEAR(TODAY()),MONTH(TODAY())+(-4),1),"YYYY-MM") -> 0 | K9: =TEXT(DATE(YEAR(TODAY()),MONTH(TODAY())+(-3),1),"YYYY-MM") -> 0 | L9: =TEXT(DATE(YEAR(TODAY()),MONTH(TODAY())+(-2),1),"YYYY-MM") -> 0 | M9: =TEXT(DATE(YEAR(TODAY()),MONTH(TODAY())+(-1),1),"YYYY-MM") -> 0 | N9: =TEXT(DATE(YEAR(TODAY()),MONTH(TODAY()),1),"YYYY-MM") -> 0
B10: Havi Cashflow | C10: =C8-C9 -> 0 | E10: Virtualis Zsebek [Auto] | H10: =IFERROR('90_Settings'!B2,"") -> 0 | I10: =IFERROR(SUMPRODUCT(('01_Transactions'!F$2:F$5000='90_Settings'!B2)*(YEAR('01_Transactions'!A$2:A$5000)=YEAR(DATE(YEAR(TODAY()),MONTH(TODAY())+(-5),1)))*(MONTH('01_Transactions'!A$2:A$5000)=MONTH(DATE(YEAR(TODAY()),MONTH(TODAY())+(-5),1)))*'01_Transactions'!L$2:L$5000),0) -> 0 | J10: =IFERROR(SUMPRODUCT(('01_Transactions'!F$2:F$5000='90_Settings'!B2)*(YEAR('01_Transactions'!A$2:A$5000)=YEAR(DATE(YEAR(TODAY()),MONTH(TODAY())+(-4),1)))*(MONTH('01_Transactions'!A$2:A$5000)=MONTH(DATE(YEAR(TODAY()),MONTH(TODAY())+(-4),1)))*'01_Transactions'!L$2:L$5000),0) -> 0 | K10: =IFERROR(SUMPRODUCT(('01_Transactions'!F$2:F$5000='90_Settings'!B2)*(YEAR('01_Transactions'!A$2:A$5000)=YEAR(DATE(YEAR(TODAY()),MONTH(TODAY())+(-3),1)))*(MONTH('01_Transactions'!A$2:A$5000)=MONTH(DATE(YEAR(TODAY()),MONTH(TODAY())+(-3),1)))*'01_Transactions'!L$2:L$5000),0) -> 0 | L10: =IFERROR(SUMPRODUCT(('01_Transactions'!F$2:F$5000='90_Settings'!B2)*(YEAR('01_Transactions'!A$2:A$5000)=YEAR(DATE(YEAR(TODAY()),MONTH(TODAY())+(-2),1)))*(MONTH('01_Transactions'!A$2:A$5000)=MONTH(DATE(YEAR(TODAY()),MONTH(TODAY())+(-2),1)))*'01_Transactions'!L$2:L$5000),0) -> 0 | M10: =IFERROR(SUMPRODUCT(('01_Transactions'!F$2:F$5000='90_Settings'!B2)*(YEAR('01_Transactions'!A$2:A$5000)=YEAR(DATE(YEAR(TODAY()),MONTH(TODAY())+(-1),1)))*(MONTH('01_Transactions'!A$2:A$5000)=MONTH(DATE(YEAR(TODAY()),MONTH(TODAY())+(-1),1)))*'01_Transactions'!L$2:L$5000),0) -> 0 | N10: =IFERROR(SUMPRODUCT(('01_Transactions'!F$2:F$5000='90_Settings'!B2)*(YEAR('01_Transactions'!A$2:A$5000)=YEAR(DATE(YEAR(TODAY()),MONTH(TODAY()),1)))*(MONTH('01_Transactions'!A$2:A$5000)=MONTH(DATE(YEAR(TODAY()),MONTH(TODAY()),1)))*'01_Transactions'!L$2:L$5000),0) -> 0
E11: =IFERROR('04_Pockets'!A2,"") -> 0 | F11: =IFERROR(SUMPRODUCT(('01_Transactions'!G$2:G$5000='04_Pockets'!A2)*'01_Transactions'!L$2:L$5000),0) -> 0 | H11: =IFERROR('90_Settings'!B3,"") -> 0 | I11: =IFERROR(SUMPRODUCT(('01_Transactions'!F$2:F$5000='90_Settings'!B3)*(YEAR('01_Transactions'!A$2:A$5000)=YEAR(DATE(YEAR(TODAY()),MONTH(TODAY())+(-5),1)))*(MONTH('01_Transactions'!A$2:A$5000)=MONTH(DATE(YEAR(TODAY()),MONTH(TODAY())+(-5),1)))*'01_Transactions'!L$2:L$5000),0) -> 0 | J11: =IFERROR(SUMPRODUCT(('01_Transactions'!F$2:F$5000='90_Settings'!B3)*(YEAR('01_Transactions'!A$2:A$5000)=YEAR(DATE(YEAR(TODAY()),MONTH(TODAY())+(-4),1)))*(MONTH('01_Transactions'!A$2:A$5000)=MONTH(DATE(YEAR(TODAY()),MONTH(TODAY())+(-4),1)))*'01_Transactions'!L$2:L$5000),0) -> 0 | K11: =IFERROR(SUMPRODUCT(('01_Transactions'!F$2:F$5000='90_Settings'!B3)*(YEAR('01_Transactions'!A$2:A$5000)=YEAR(DATE(YEAR(TODAY()),MONTH(TODAY())+(-3),1)))*(MONTH('01_Transactions'!A$2:A$5000)=MONTH(DATE(YEAR(TODAY()),MONTH(TODAY())+(-3),1)))*'01_Transactions'!L$2:L$5000),0) -> 0 | L11: =IFERROR(SUMPRODUCT(('01_Transactions'!F$2:F$5000='90_Settings'!B3)*(YEAR('01_Transactions'!A$2:A$5000)=YEAR(DATE(YEAR(TODAY()),MONTH(TODAY())+(-2),1)))*(MONTH('01_Transactions'!A$2:A$5000)=MONTH(DATE(YEAR(TODAY()),MONTH(TODAY())+(-2),1)))*'01_Transactions'!L$2:L$5000),0) -> 0 | M11: =IFERROR(SUMPRODUCT(('01_Transactions'!F$2:F$5000='90_Settings'!B3)*(YEAR('01_Transactions'!A$2:A$5000)=YEAR(DATE(YEAR(TODAY()),MONTH(TODAY())+(-1),1)))*(MONTH('01_Transactions'!A$2:A$5000)=MONTH(DATE(YEAR(TODAY()),MONTH(TODAY())+(-1),1)))*'01_Transactions'!L$2:L$5000),0) -> 0 | N11: =IFERROR(SUMPRODUCT(('01_Transactions'!F$2:F$5000='90_Settings'!B3)*(YEAR('01_Transactions'!A$2:A$5000)=YEAR(DATE(YEAR(TODAY()),MONTH(TODAY()),1)))*(MONTH('01_Transactions'!A$2:A$5000)=MONTH(DATE(YEAR(TODAY()),MONTH(TODAY()),1)))*'01_Transactions'!L$2:L$5000),0) -> 0
E12: =IFERROR('04_Pockets'!A3,"") -> 0 | F12: =IFERROR(SUMPRODUCT(('01_Transactions'!G$2:G$5000='04_Pockets'!A3)*'01_Transactions'!L$2:L$5000),0) -> 0 | H12: =IFERROR('90_Settings'!B4,"") -> 0 | I12: =IFERROR(SUMPRODUCT(('01_Transactions'!F$2:F$5000='90_Settings'!B4)*(YEAR('01_Transactions'!A$2:A$5000)=YEAR(DATE(YEAR(TODAY()),MONTH(TODAY())+(-5),1)))*(MONTH('01_Transactions'!A$2:A$5000)=MONTH(DATE(YEAR(TODAY()),MONTH(TODAY())+(-5),1)))*'01_Transactions'!L$2:L$5000),0) -> 0 | J12: =IFERROR(SUMPRODUCT(('01_Transactions'!F$2:F$5000='90_Settings'!B4)*(YEAR('01_Transactions'!A$2:A$5000)=YEAR(DATE(YEAR(TODAY()),MONTH(TODAY())+(-4),1)))*(MONTH('01_Transactions'!A$2:A$5000)=MONTH(DATE(YEAR(TODAY()),MONTH(TODAY())+(-4),1)))*'01_Transactions'!L$2:L$5000),0) -> 0 | K12: =IFERROR(SUMPRODUCT(('01_Transactions'!F$2:F$5000='90_Settings'!B4)*(YEAR('01_Transactions'!A$2:A$5000)=YEAR(DATE(YEAR(TODAY()),MONTH(TODAY())+(-3),1)))*(MONTH('01_Transactions'!A$2:A$5000)=MONTH(DATE(YEAR(TODAY()),MONTH(TODAY())+(-3),1)))*'01_Transactions'!L$2:L$5000),0) -> 0 | L12: =IFERROR(SUMPRODUCT(('01_Transactions'!F$2:F$5000='90_Settings'!B4)*(YEAR('01_Transactions'!A$2:A$5000)=YEAR(DATE(YEAR(TODAY()),MONTH(TODAY())+(-2),1)))*(MONTH('01_Transactions'!A$2:A$5000)=MONTH(DATE(YEAR(TODAY()),MONTH(TODAY())+(-2),1)))*'01_Transactions'!L$2:L$5000),0) -> 0 | M12: =IFERROR(SUMPRODUCT(('01_Transactions'!F$2:F$5000='90_Settings'!B4)*(YEAR('01_Transactions'!A$2:A$5000)=YEAR(DATE(YEAR(TODAY()),MONTH(TODAY())+(-1),1)))*(MONTH('01_Transactions'!A$2:A$5000)=MONTH(DATE(YEAR(TODAY()),MONTH(TODAY())+(-1),1)))*'01_Transactions'!L$2:L$5000),0) -> 0 | N12: =IFERROR(SUMPRODUCT(('01_Transactions'!F$2:F$5000='90_Settings'!B4)*(YEAR('01_Transactions'!A$2:A$5000)=YEAR(DATE(YEAR(TODAY()),MONTH(TODAY()),1)))*(MONTH('01_Transactions'!A$2:A$5000)=MONTH(DATE(YEAR(TODAY()),MONTH(TODAY()),1)))*'01_Transactions'!L$2:L$5000),0) -> 0
E13: =IFERROR('04_Pockets'!A4,"") -> 0 | F13: =IFERROR(SUMPRODUCT(('01_Transactions'!G$2:G$5000='04_Pockets'!A4)*'01_Transactions'!L$2:L$5000),0) -> 0 | H13: =IFERROR('90_Settings'!B5,"") -> 0 | I13: =IFERROR(SUMPRODUCT(('01_Transactions'!F$2:F$5000='90_Settings'!B5)*(YEAR('01_Transactions'!A$2:A$5000)=YEAR(DATE(YEAR(TODAY()),MONTH(TODAY())+(-5),1)))*(MONTH('01_Transactions'!A$2:A$5000)=MONTH(DATE(YEAR(TODAY()),MONTH(TODAY())+(-5),1)))*'01_Transactions'!L$2:L$5000),0) -> 0 | J13: =IFERROR(SUMPRODUCT(('01_Transactions'!F$2:F$5000='90_Settings'!B5)*(YEAR('01_Transactions'!A$2:A$5000)=YEAR(DATE(YEAR(TODAY()),MONTH(TODAY())+(-4),1)))*(MONTH('01_Transactions'!A$2:A$5000)=MONTH(DATE(YEAR(TODAY()),MONTH(TODAY())+(-4),1)))*'01_Transactions'!L$2:L$5000),0) -> 0 | K13: =IFERROR(SUMPRODUCT(('01_Transactions'!F$2:F$5000='90_Settings'!B5)*(YEAR('01_Transactions'!A$2:A$5000)=YEAR(DATE(YEAR(TODAY()),MONTH(TODAY())+(-3),1)))*(MONTH('01_Transactions'!A$2:A$5000)=MONTH(DATE(YEAR(TODAY()),MONTH(TODAY())+(-3),1)))*'01_Transactions'!L$2:L$5000),0) -> 0 | L13: =IFERROR(SUMPRODUCT(('01_Transactions'!F$2:F$5000='90_Settings'!B5)*(YEAR('01_Transactions'!A$2:A$5000)=YEAR(DATE(YEAR(TODAY()),MONTH(TODAY())+(-2),1)))*(MONTH('01_Transactions'!A$2:A$5000)=MONTH(DATE(YEAR(TODAY()),MONTH(TODAY())+(-2),1)))*'01_Transactions'!L$2:L$5000),0) -> 0 | M13: =IFERROR(SUMPRODUCT(('01_Transactions'!F$2:F$5000='90_Settings'!B5)*(YEAR('01_Transactions'!A$2:A$5000)=YEAR(DATE(YEAR(TODAY()),MONTH(TODAY())+(-1),1)))*(MONTH('01_Transactions'!A$2:A$5000)=MONTH(DATE(YEAR(TODAY()),MONTH(TODAY())+(-1),1)))*'01_Transactions'!L$2:L$5000),0) -> 0 | N13: =IFERROR(SUMPRODUCT(('01_Transactions'!F$2:F$5000='90_Settings'!B5)*(YEAR('01_Transactions'!A$2:A$5000)=YEAR(DATE(YEAR(TODAY()),MONTH(TODAY()),1)))*(MONTH('01_Transactions'!A$2:A$5000)=MONTH(DATE(YEAR(TODAY()),MONTH(TODAY()),1)))*'01_Transactions'!L$2:L$5000),0) -> 0
H14: =IFERROR('90_Settings'!B6,"") -> 0 | I14: =IFERROR(SUMPRODUCT(('01_Transactions'!F$2:F$5000='90_Settings'!B6)*(YEAR('01_Transactions'!A$2:A$5000)=YEAR(DATE(YEAR(TODAY()),MONTH(TODAY())+(-5),1)))*(MONTH('01_Transactions'!A$2:A$5000)=MONTH(DATE(YEAR(TODAY()),MONTH(TODAY())+(-5),1)))*'01_Transactions'!L$2:L$5000),0) -> 0 | J14: =IFERROR(SUMPRODUCT(('01_Transactions'!F$2:F$5000='90_Settings'!B6)*(YEAR('01_Transactions'!A$2:A$5000)=YEAR(DATE(YEAR(TODAY()),MONTH(TODAY())+(-4),1)))*(MONTH('01_Transactions'!A$2:A$5000)=MONTH(DATE(YEAR(TODAY()),MONTH(TODAY())+(-4),1)))*'01_Transactions'!L$2:L$5000),0) -> 0 | K14: =IFERROR(SUMPRODUCT(('01_Transactions'!F$2:F$5000='90_Settings'!B6)*(YEAR('01_Transactions'!A$2:A$5000)=YEAR(DATE(YEAR(TODAY()),MONTH(TODAY())+(-3),1)))*(MONTH('01_Transactions'!A$2:A$5000)=MONTH(DATE(YEAR(TODAY()),MONTH(TODAY())+(-3),1)))*'01_Transactions'!L$2:L$5000),0) -> 0 | L14: =IFERROR(SUMPRODUCT(('01_Transactions'!F$2:F$5000='90_Settings'!B6)*(YEAR('01_Transactions'!A$2:A$5000)=YEAR(DATE(YEAR(TODAY()),MONTH(TODAY())+(-2),1)))*(MONTH('01_Transactions'!A$2:A$5000)=MONTH(DATE(YEAR(TODAY()),MONTH(TODAY())+(-2),1)))*'01_Transactions'!L$2:L$5000),0) -> 0 | M14: =IFERROR(SUMPRODUCT(('01_Transactions'!F$2:F$5000='90_Settings'!B6)*(YEAR('01_Transactions'!A$2:A$5000)=YEAR(DATE(YEAR(TODAY()),MONTH(TODAY())+(-1),1)))*(MONTH('01_Transactions'!A$2:A$5000)=MONTH(DATE(YEAR(TODAY()),MONTH(TODAY())+(-1),1)))*'01_Transactions'!L$2:L$5000),0) -> 0 | N14: =IFERROR(SUMPRODUCT(('01_Transactions'!F$2:F$5000='90_Settings'!B6)*(YEAR('01_Transactions'!A$2:A$5000)=YEAR(DATE(YEAR(TODAY()),MONTH(TODAY()),1)))*(MONTH('01_Transactions'!A$2:A$5000)=MONTH(DATE(YEAR(TODAY()),MONTH(TODAY()),1)))*'01_Transactions'!L$2:L$5000),0) -> 0
H15: =IFERROR('90_Settings'!B7,"") -> 0 | I15: =IFERROR(SUMPRODUCT(('01_Transactions'!F$2:F$5000='90_Settings'!B7)*(YEAR('01_Transactions'!A$2:A$5000)=YEAR(DATE(YEAR(TODAY()),MONTH(TODAY())+(-5),1)))*(MONTH('01_Transactions'!A$2:A$5000)=MONTH(DATE(YEAR(TODAY()),MONTH(TODAY())+(-5),1)))*'01_Transactions'!L$2:L$5000),0) -> 0 | J15: =IFERROR(SUMPRODUCT(('01_Transactions'!F$2:F$5000='90_Settings'!B7)*(YEAR('01_Transactions'!A$2:A$5000)=YEAR(DATE(YEAR(TODAY()),MONTH(TODAY())+(-4),1)))*(MONTH('01_Transactions'!A$2:A$5000)=MONTH(DATE(YEAR(TODAY()),MONTH(TODAY())+(-4),1)))*'01_Transactions'!L$2:L$5000),0) -> 0 | K15: =IFERROR(SUMPRODUCT(('01_Transactions'!F$2:F$5000='90_Settings'!B7)*(YEAR('01_Transactions'!A$2:A$5000)=YEAR(DATE(YEAR(TODAY()),MONTH(TODAY())+(-3),1)))*(MONTH('01_Transactions'!A$2:A$5000)=MONTH(DATE(YEAR(TODAY()),MONTH(TODAY())+(-3),1)))*'01_Transactions'!L$2:L$5000),0) -> 0 | L15: =IFERROR(SUMPRODUCT(('01_Transactions'!F$2:F$5000='90_Settings'!B7)*(YEAR('01_Transactions'!A$2:A$5000)=YEAR(DATE(YEAR(TODAY()),MONTH(TODAY())+(-2),1)))*(MONTH('01_Transactions'!A$2:A$5000)=MONTH(DATE(YEAR(TODAY()),MONTH(TODAY())+(-2),1)))*'01_Transactions'!L$2:L$5000),0) -> 0 | M15: =IFERROR(SUMPRODUCT(('01_Transactions'!F$2:F$5000='90_Settings'!B7)*(YEAR('01_Transactions'!A$2:A$5000)=YEAR(DATE(YEAR(TODAY()),MONTH(TODAY())+(-1),1)))*(MONTH('01_Transactions'!A$2:A$5000)=MONTH(DATE(YEAR(TODAY()),MONTH(TODAY())+(-1),1)))*'01_Transactions'!L$2:L$5000),0) -> 0 | N15: =IFERROR(SUMPRODUCT(('01_Transactions'!F$2:F$5000='90_Settings'!B7)*(YEAR('01_Transactions'!A$2:A$5000)=YEAR(DATE(YEAR(TODAY()),MONTH(TODAY()),1)))*(MONTH('01_Transactions'!A$2:A$5000)=MONTH(DATE(YEAR(TODAY()),MONTH(TODAY()),1)))*'01_Transactions'!L$2:L$5000),0) -> 0

Sheet 01_Transactions
A1: Date | B1: Type | C1: Account | D1: Amount | E1: Currency | F1: Category | G1: Pocket | H1: Merchant | I1: Owner | J1: Note | K1: ID 🔒 | L1: BaseAmount 🔒 | M1: CreatedAt 🔒
A2: 2024-01-08 | B2: Expense | C2: OTP számla | D2: 39591 | E2: HUF | F2: Business befektetés | I2: Adam | J2: Mezek és táska | K2: TX-1448 | L2: =D2*N2 -> 0 | N2: =IF(E2="HUF", 1, IFERROR(VLOOKUP(A2&E2, '91_Data_ExRates'!A:D, 4, FALSE), 1)) -> 0
A3: 2024-01-22 | B3: Expense | C3: Készpénz | D3: 500 | E3: HUF | F3: Ajándék | I3: Adam | J3: Futár | K3: TX-1445 | L3: =D3*N3 -> 0 | N3: =IF(E3="HUF", 1, IFERROR(VLOOKUP(A3&E3, '91_Data_ExRates'!A:D, 4, FALSE), 1)) -> 0
A4: 2024-01-22 | B4: Expense | C4: OTP számla | D4: 220 | E4: HUF | F4: Közlekedés | I4: Adam | J4: Gdl | K4: TX-1446 | L4: =D4*N4 -> 0 | N4: =IF(E4="HUF", 1, IFERROR(VLOOKUP(A4&E4, '91_Data_ExRates'!A:D, 4, FALSE), 1)) -> 0
A5: 2024-01-22 | B5: Expense | C5: OTP számla | D5: 220 | E5: HUF | F5: Közlekedés | I5: Adam | J5: GDL busz | K5: TX-1447 | L5: =D5*N5 -> 0 | N5: =IF(E5="HUF", 1, IFERROR(VLOOKUP(A5&E5, '91_Data_ExRates'!A:D, 4, FALSE), 1)) -> 0
A6: 2024-01-23 | B6: Expense | C6: Készpénz | D6: 2000 | E6: HUF | F6: Étel-ital | I6: Adam | J6: Algir gyros @ Dönercos | K6: TX-1444 | L6: =D6*N6 -> 0 | N6: =IF(E6="HUF", 1, IFERROR(VLOOKUP(A6&E6, '91_Data_ExRates'!A:D, 4, FALSE), 1)) -> 0
A7: 2024-01-23 | B7: Expense | C7: Készpénz | D7: 850 | E7: HUF | F7: Luxus, szórakozás | I7: Adam | J7: Dreher @ pajta pub | K7: TX-1443 | L7: =D7*N7 -> 0 | N7: =IF(E7="HUF", 1, IFERROR(VLOOKUP(A7&E7, '91_Data_ExRates'!A:D, 4, FALSE), 1)) -> 0
A8: 2024-01-24 | B8: Expense | C8: OTP számla | D8: 220 | E8: HUF | F8: Közlekedés | I8: Adam | J8: Gdl | K8: TX-1442 | L8: =D8*N8 -> 0 | N8: =IF(E8="HUF", 1, IFERROR(VLOOKUP(A8&E8, '91_Data_ExRates'!A:D, 4, FALSE), 1)) -> 0
A9: 2024-01-25 | B9: Income | C9: OTP számla | D9: 15000 | E9: HUF | F9: Üzletelés | I9: Adam | J9: Juventus vendég mez | K9: TX-1519 | L9: =D9*N9 -> 0 | N9: =IF(E9="HUF", 1, IFERROR(VLOOKUP(A9&E9, '91_Data_ExRates'!A:D, 4, FALSE), 1)) -> 0
A10: 2024-01-26 | B10: Income | C10: Készpénz | D10: 50000 | E10: HUF | F10: Ajándék | I10: Adam | J10: Barcelona zsebpénz - Bözsi mama | K10: TX-1518 | L10: =D10*N10 -> 0 | N10: =IF(E10="HUF", 1, IFERROR(VLOOKUP(A10&E10, '91_Data_ExRates'!A:D, 4, FALSE), 1)) -> 0
A11: 2024-01-26 | B11: Income | C11: Készpénz | D11: 20000 | E11: HUF | F11: Ajándék | I11: Adam | J11: Barcelona zsebpénz - Zsuzsi mama | K11: TX-1517 | L11: =D11*N11 -> 0 | N11: =IF(E11="HUF", 1, IFERROR(VLOOKUP(A11&E11, '91_Data_ExRates'!A:D, 4, FALSE), 1)) -> 0
A12: 2024-02-01 | B12: Expense | C12: Készpénz | D12: 890 | E12: HUF | F12: Luxus, szórakozás | I12: Adam | J12: Sör @ Blokk | K12: TX-1441 | L12: =D12*N12 -> 0 | N12: =IF(E12="HUF", 1, IFERROR(VLOOKUP(A12&E12, '91_Data_ExRates'!A:D, 4, FALSE), 1)) -> 0
A13: 2024-02-01 | B13: Expense | C13: Készpénz | D13: 1490 | E13: HUF | F13: Luxus, szórakozás | I13: Adam | J13: Daiquiri @ Blokk | K13: TX-1440 | L13: =D13*N13 -> 0 | N13: =IF(E13="HUF", 1, IFERROR(VLOOKUP(A13&E13, '91_Data_ExRates'!A:D, 4, FALSE), 1)) -> 0
... A23: 2024-02-13 | B23: Expense | C23: OTP számla | D23: 2587 | E23: HUF | F23: Business befektetés | I23: Adam | J23: EUR átváltas költségei | K23: TX-1431 | L23: =D23*N23 -> 0 | N23: =IF(E23="HUF", 1, IFERROR(VLOOKUP(A23&E23, '91_Data_ExRates'!A:D, 4, FALSE), 1)) -> 0
A24: 2024-02-13 | B24: Transfer | C24: OTP számla | D24: 193641.55 | E24: HUF | I24: Adam | K24: TX-1551 | L24: =D24*N24 -> 0 | N24: =IF(E24="HUF", 1, IFERROR(VLOOKUP(A24&E24, '91_Data_ExRates'!A:D, 4, FALSE), 1)) -> 0
A25: 2024-02-15 | B25: Expense | C25: OTP számla | D25: 292 | E25: HUF | F25: Egyéb | I25: Adam | J25: Otp díj | K25: TX-1430 | L25: =D25*N25 -> 0 | N25: =IF(E25="HUF", 1, IFERROR(VLOOKUP(A25&E25, '91_Data_ExRates'!A:D, 4, FALSE), 1)) -> 0
A26: 2024-02-15 | B26: Transfer | C26: OTP számla | D26: 50000 | E26: HUF | I26: Adam | K26: TX-1550 | L26: =D26*N26 -> 0 | N26: =IF(E26="HUF", 1, IFERROR(VLOOKUP(A26&E26, '91_Data_ExRates'!A:D, 4, FALSE), 1)) -> 0
A27: 2024-02-16 | B27: Expense | C27: Készpénz | D27: 1900 | E27: HUF | F27: Étel-ital | I27: Adam | J27: Mekdo | K27: TX-1429 | L27: =D27*N27 -> 0 | N27: =IF(E27="HUF", 1, IFERROR(VLOOKUP(A27&E27, '91_Data_ExRates'!A:D, 4, FALSE), 1)) -> 0
A28: 2024-02-17 | B28: Expense | C28: Készpénz | D28: 680 | E28: HUF | F28: Luxus, szórakozás | I28: Adam | K28: TX-1428 | L28: =D28*N28 -> 0 | N28: =IF(E28="HUF", 1, IFERROR(VLOOKUP(A28&E28, '91_Data_ExRates'!A:D, 4, FALSE), 1)) -> 0
A29: 2024-02-21 | B29: Expense | C29: Készpénz | D29: 850 | E29: HUF | F29: Luxus, szórakozás | I29: Adam | J29: Pomyva nagyfröccs | K29: TX-1426 | L29: =D29*N29 -> 0 | N29: =IF(E29="HUF", 1, IFERROR(VLOOKUP(A29&E29, '91_Data_ExRates'!A:D, 4, FALSE), 1)) -> 0
A30: 2024-02-21 | B30: Expense | C30: Készpénz | D30: 850 | E30: HUF | F30: Luxus, szórakozás | I30: Adam | J30: Borpatika házmester | K30: TX-1427 | L30: =D30*N30 -> 0 | N30: =IF(E30="HUF", 1, IFERROR(VLOOKUP(A30&E30, '91_Data_ExRates'!A:D, 4, FALSE), 1)) -> 0
A31: 2024-02-21 | B31: Expense | C31: Készpénz | D31: 1600 | E31: HUF | F31: Étel-ital | I31: Adam | J31: Karimi gyrostál felezés | K31: TX-1425 | L31: =D31*N31 -> 0 | N31: =IF(E31="HUF", 1, IFERROR(VLOOKUP(A31&E31, '91_Data_ExRates'!A:D, 4, FALSE), 1)) -> 0
A32: 2024-02-23 | B32: Income | C32: Államkincstár | D32: 225644 | E32: HUF | F32: Kamat | I32: Adam | K32: TX-1514 | L32: =D32*N32 -> 0 | N32: =IF(E32="HUF", 1, IFERROR(VLOOKUP(A32&E32, '91_Data_ExRates'!A:D, 4, FALSE), 1)) -> 0
A33: 2024-02-23 | B33: Income | C33: Készpénz | D33: 20000 | E33: HUF | F33: Ajándék | I33: Adam | J33: Anya zsebpénz | K33: TX-1515 | L33: =D33*N33 -> 0 | N33: =IF(E33="HUF", 1, IFERROR(VLOOKUP(A33&E33, '91_Data_ExRates'!A:D, 4, FALSE), 1)) -> 0
A34: 2024-02-23 | B34: Expense | C34: Készpénz | D34: 20000 | E34: HUF | F34: Étel-ital | I34: Adam | J34: Timi hotpot | K34: TX-1424 | L34: =D34*N34 -> 0 | N34: =IF(E34="HUF", 1, IFERROR(VLOOKUP(A34&E34, '91_Data_ExRates'!A:D, 4, FALSE), 1)) -> 0
A35: 2024-03-01 | B35: Transfer | C35: Államkincstár | D35: 225644 | E35: HUF | I35: Adam | K35: TX-1549 | L35: =D35*N35 -> 0 | N35: =IF(E35="HUF", 1, IFERROR(VLOOKUP(A35&E35, '91_Data_ExRates'!A:D, 4, FALSE), 1)) -> 0
A36: 2024-03-02 | B36: Expense | C36: OTP számla | D36: 1590 | E36: HUF | F36: Luxus, szórakozás | I36: Adam | J36: Pogi @ MVM - kóla | K36: TX-1422 | L36: =D36*N36 -> 0 | N36: =IF(E36="HUF", 1, IFERROR(VLOOKUP(A36&E36, '91_Data_ExRates'!A:D, 4, FALSE), 1)) -> 0
A37: 2024-03-02 | B37: Expense | C37: OTP számla | D37: 190 | E37: HUF | F37: Közlekedés | I37: Adam | J37: Volán GDL | K37: TX-1423 | L37: =D37*N37 -> 0 | N37: =IF(E37="HUF", 1, IFERROR(VLOOKUP(A37&E37, '91_Data_ExRates'!A:D, 4, FALSE), 1)) -> 0
A38: 2024-03-04 | B38: Expense | C38: OTP számla | D38: 1790 | E38: HUF | F38: Luxus, szórakozás | I38: Adam | J38: Sör @ udvarROM | K38: TX-1421 | L38: =D38*N38 -> 0 | N38: =IF(E38="HUF", 1, IFERROR(VLOOKUP(A38&E38, '91_Data_ExRates'!A:D, 4, FALSE), 1)) -> 0
A39: 2024-03-06 | B39: Expense | C39: Készpénz | D39: 26000 | E39: HUF | F39: Étel-ital | I39: Adam | J39: Hotpot bevásárlás | K39: TX-1420 | L39: =D39*N39 -> 0 | N39: =IF(E39="HUF", 1, IFERROR(VLOOKUP(A39&E39, '91_Data_ExRates'!A:D, 4, FALSE), 1)) -> 0
A40: 2024-03-06 | B40: Income | C40: Ajándékutalvány | D40: 10000 | E40: HUF | F40: Ajándék | I40: Adam | J40: Ajándékutalvány makro xdd | K40: TX-1513 | L40: =D40*N40 -> 0 | N40: =IF(E40="HUF", 1, IFERROR(VLOOKUP(A40&E40, '91_Data_ExRates'!A:D, 4, FALSE), 1)) -> 0
A41: 2024-03-07 | B41: Expense | C41: Készpénz | D41: 1900 | E41: HUF | F41: Luxus, szórakozás | I41: Adam | J41: Két sör + borravaló | K41: TX-1419 | L41: =D41*N41 -> 0 | N41: =IF(E41="HUF", 1, IFERROR(VLOOKUP(A41&E41, '91_Data_ExRates'!A:D, 4, FALSE), 1)) -> 0
A42: 2024-03-07 | B42: Income | C42: OTP számla | D42: 160000 | E42: HUF | F42: Ösztöndíj | I42: Adam | J42: Kéthavi ösztöndíj | K42: TX-1512 | L42: =D42*N42 -> 0 | N42: =IF(E42="HUF", 1, IFERROR(VLOOKUP(A42&E42, '91_Data_ExRates'!A:D, 4, FALSE), 1)) -> 0
A43: 2024-03-07 | B43: Expense | C43: Készpénz | D43: 3700 | E43: HUF | F43: Étel-ital | I43: Adam | J43: tortilla + falafel tál @ Karimi | K43: TX-1418 | L43: =D43*N43 -> 0 | N43: =IF(E43="HUF", 1, IFERROR(VLOOKUP(A43&E43, '91_Data_ExRates'!A:D, 4, FALSE), 1)) -> 0
A44: 2024-03-08 | B44: Expense | C44: OTP számla | D44: 190 | E44: HUF | F44: Közlekedés | I44: Adam | J44: GDL | K44: TX-1417 | L44: =D44*N44 -> 0 | N44: =IF(E44="HUF", 1, IFERROR(VLOOKUP(A44&E44, '91_Data_ExRates'!A:D, 4, FALSE), 1)) -> 0
A45: 2024-03-09 | B45: Income | C45: Készpénz | D45: 3800 | E45: HUF | F45: Egyéb | I45: Adam | J45: hotpot | K45: TX-1510 | L45: =D45*N45 -> 0 | N45: =IF(E45="HUF", 1, IFERROR(VLOOKUP(A45&E45, '91_Data_ExRates'!A:D, 4, FALSE), 1)) -> 0
A46: 2024-03-09 | B46: Income | C46: OTP számla | D46: 21900 | E46: HUF | F46: Egyéb | I46: Adam | J46: Hotpot bevásárlás+torta törlesztés | K46: TX-1511 | L46: =D46*N46 -> 0 | N46: =IF(E46="HUF", 1, IFERROR(VLOOKUP(A46&E46, '91_Data_ExRates'!A:D, 4, FALSE), 1)) -> 0
A47: 2024-03-14 | B47: Expense | C47: Készpénz | D47: 1400 | E47: HUF | F47: Luxus, szórakozás | I47: Adam | J47: Staropramen @ ZICCER | K47: TX-1416 | L47: =D47*N47 -> 0 | N47: =IF(E47="HUF", 1, IFERROR(VLOOKUP(A47&E47, '91_Data_ExRates'!A:D, 4, FALSE), 1)) -> 0
A48: 2024-03-16 | B48: Expense | C48: OTP számla | D48: 190 | E48: HUF | F48: Közlekedés | I48: Adam | K48: TX-1415 | L48: =D48*N48 -> 0 | N48: =IF(E48="HUF", 1, IFERROR(VLOOKUP(A48&E48, '91_Data_ExRates'!A:D, 4, FALSE), 1)) -> 0
A49: 2024-03-17 | B49: Transfer | C49: Ajándékutalvány | D49: 10000 | E49: HUF | I49: Adam | J49: Anya trade | K49: TX-1548 | L49: =D49*N49 -> 0 | N49: =IF(E49="HUF", 1, IFERROR(VLOOKUP(A49&E49, '91_Data_ExRates'!A:D, 4, FALSE), 1)) -> 0
A50: 2024-03-25 | B50: Expense | C50: OTP számla | D50: 3680 | E50: HUF | F50: Egyéb | I50: Adam | J50: Shein mate + air fryer | K50: TX-1414 | L50: =D50*N50 -> 0 | N50: =IF(E50="HUF", 1, IFERROR(VLOOKUP(A50&E50, '91_Data_ExRates'!A:D, 4, FALSE), 1)) -> 0
A51: 2024-03-27 | B51: Expense | C51: Készpénz | D51: 1400 | E51: HUF | F51: Luxus, szórakozás | I51: Adam | J51: Robi | K51: TX-1413 | L51: =D51*N51 -> 0 | N51: =IF(E51="HUF", 1, IFERROR(VLOOKUP(A51&E51, '91_Data_ExRates'!A:D, 4, FALSE), 1)) -> 0
A52: 2024-03-28 | B52: Expense | C52: OTP számla | D52: 190 | E52: HUF | F52: Közlekedés | I52: Adam | K52: TX-1412 | L52: =D52*N52 -> 0 | N52: =IF(E52="HUF", 1, IFERROR(VLOOKUP(A52&E52, '91_Data_ExRates'!A:D, 4, FALSE), 1)) -> 0
A53: 2024-04-01 | B53: Income | C53: Készpénz | D53: 40000 | E53: HUF | F53: Ajándék | I53: Adam | J53: Zsuzsi mama locsolás | K53: TX-1509 | L53: =D53*N53 -> 0 | N53: =IF(E53="HUF", 1, IFERROR(VLOOKUP(A53&E53, '91_Data_ExRates'!A:D, 4, FALSE), 1)) -> 0
A54: 2024-04-01 | B54: Income | C54: Készpénz | D54: 30000 | E54: HUF | F54: Ajándék | I54: Adam | J54: Bözsi mama húsvét | K54: TX-1508 | L54: =D54*N54 -> 0 | N54: =IF(E54="HUF", 1, IFERROR(VLOOKUP(A54&E54, '91_Data_ExRates'!A:D, 4, FALSE), 1)) -> 0
A55: 2024-04-02 | B55: Expense | C55: Készpénz | D55: 1900 | E55: HUF | F55: Egészség | I55: Adam | J55: Condom | K55: TX-1411 | L55: =D55*N55 -> 0 | N55: =IF(E55="HUF", 1, IFERROR(VLOOKUP(A55&E55, '91_Data_ExRates'!A:D, 4, FALSE), 1)) -> 0
A56: 2024-04-04 | B56: Expense | C56: Készpénz | D56: 1900 | E56: HUF | F56: Étel-ital | I56: Adam | J56: Falafel king street | K56: TX-1410 | L56: =D56*N56 -> 0 | N56: =IF(E56="HUF", 1, IFERROR(VLOOKUP(A56&E56, '91_Data_ExRates'!A:D, 4, FALSE), 1)) -> 0
A57: 2024-04-05 | B57: Income | C57: OTP számla | D57: 8900 | E57: HUF | F57: Üzletelés | I57: Adam | J57: WHU mez | K57: TX-1507 | L57: =D57*N57 -> 0 | N57: =IF(E57="HUF", 1, IFERROR(VLOOKUP(A57&E57, '91_Data_ExRates'!A:D, 4, FALSE), 1)) -> 0
A58: 2024-04-09 | B58: Income | C58: OTP számla | D58: 80000 | E58: HUF | F58: Ösztöndíj | I58: Adam | K58: TX-1506 | L58: =D58*N58 -> 0 | N58: =IF(E58="HUF", 1, IFERROR(VLOOKUP(A58&E58, '91_Data_ExRates'!A:D, 4, FALSE), 1)) -> 0
A59: 2024-04-12 | B59: Expense | C59: OTP számla | D59: 220 | E59: HUF | F59: Közlekedés | I59: Adam | K59: TX-1407 | L59: =D59*N59 -> 0 | N59: =IF(E59="HUF", 1, IFERROR(VLOOKUP(A59&E59, '91_Data_ExRates'!A:D, 4, FALSE), 1)) -> 0
A60: 2024-04-12 | B60: Expense | C60: OTP számla | D60: 1350 | E60: HUF | F60: Étel-ital | I60: Adam | J60: Munch | K60: TX-1408 | L60: =D60*N60 -> 0 | N60: =IF(E60="HUF", 1, IFERROR(VLOOKUP(A60&E60, '91_Data_ExRates'!A:D, 4, FALSE), 1)) -> 0
A61: 2024-04-12 | B61: Expense | C61: Készpénz | D61: 2000 | E61: HUF | F61: Luxus, szórakozás | I61: Adam | J61: Fagyi @ Naplázs | K61: TX-1409 | L61: =D61*N61 -> 0 | N61: =IF(E61="HUF", 1, IFERROR(VLOOKUP(A61&E61, '91_Data_ExRates'!A:D, 4, FALSE), 1)) -> 0
A62: 2024-04-16 | B62: Expense | C62: OTP számla | D62: 1615 | E62: HUF | F62: Étel-ital | I62: Adam | J62: Munch szülőknek | K62: TX-1406 | L62: =D62*N62 -> 0 | N62: =IF(E62="HUF", 1, IFERROR(VLOOKUP(A62&E62, '91_Data_ExRates'!A:D, 4, FALSE), 1)) -> 0
A63: 2024-04-18 | B63: Expense | C63: Készpénz | D63: 1040 | E63: HUF | F63: Luxus, szórakozás | I63: Adam | J63: Búzasör @ GosSip | K63: TX-1403 | L63: =D63*N63 -> 0 | N63: =IF(E63="HUF", 1, IFERROR(VLOOKUP(A63&E63, '91_Data_ExRates'!A:D, 4, FALSE), 1)) -> 0
A64: 2024-04-18 | B64: Expense | C64: OTP számla | D64: 2570 | E64: HUF | F64: Luxus, szórakozás | I64: Adam | J64: Burger king | K64: TX-1405 | L64: =D64*N64 -> 0 | N64: =IF(E64="HUF", 1, IFERROR(VLOOKUP(A64&E64, '91_Data_ExRates'!A:D, 4, FALSE), 1)) -> 0
A65: 2024-04-18 | B65: Expense | C65: Készpénz | D65: 1000 | E65: HUF | F65: Luxus, szórakozás | I65: Adam | J65: Mézes (?) - menü (sör + tabasco vodka) | K65: TX-1402 | L65: =D65*N65 -> 0 | N65: =IF(E65="HUF", 1, IFERROR(VLOOKUP(A65&E65, '91_Data_ExRates'!A:D, 4, FALSE), 1)) -> 0
A66: 2024-04-18 | B66: Expense | C66: Készpénz | D66: 800 | E66: HUF | F66: Luxus, szórakozás | I66: Adam | J66: Soproni @ Albert | K66: TX-1401 | L66: =D66*N66 -> 0 | N66: =IF(E66="HUF", 1, IFERROR(VLOOKUP(A66&E66, '91_Data_ExRates'!A:D, 4, FALSE), 1)) -> 0
A67: 2024-04-18 | B67: Expense | C67: Készpénz | D67: 1470 | E67: HUF | F67: Luxus, szórakozás | I67: Adam | J67: Sör + hubi kombó @ GosSip | K67: TX-1404 | L67: =D67*N67 -> 0 | N67: =IF(E67="HUF", 1, IFERROR(VLOOKUP(A67&E67, '91_Data_ExRates'!A:D, 4, FALSE), 1)) -> 0
A68: 2024-04-26 | B68: Expense | C68: Készpénz | D68: 2900 | E68: HUF | F68: Luxus, szórakozás | I68: Adam | J68: Kör @ all-inn | K68: TX-1400 | L68: =D68*N68 -> 0 | N68: =IF(E68="HUF", 1, IFERROR(VLOOKUP(A68&E68, '91_Data_ExRates'!A:D, 4, FALSE), 1)) -> 0
A69: 2024-04-26 | B69: Expense | C69: Készpénz | D69: 1850 | E69: HUF | F69: Étel-ital | I69: Adam | J69: Kálvin kebab | K69: TX-1399 | L69: =D69*N69 -> 0 | N69: =IF(E69="HUF", 1, IFERROR(VLOOKUP(A69&E69, '91_Data_ExRates'!A:D, 4, FALSE), 1)) -> 0
A70: 2024-04-29 | B70: Expense | C70: OTP számla | D70: 900 | E70: HUF | F70: Étel-ital | I70: Adam | J70: Trio pizza munch | K70: TX-1398 | L70: =D70*N70 -> 0 | N70: =IF(E70="HUF", 1, IFERROR(VLOOKUP(A70&E70, '91_Data_ExRates'!A:D, 4, FALSE), 1)) -> 0
A71: 2024-05-02 | B71: Expense | C71: OTP számla | D71: 9460 | E71: HUF | F71: Ajándék | I71: Adam | J71: Mittelwasser pólók részem | K71: TX-1397 | L71: =D71*N71 -> 0 | N71: =IF(E71="HUF", 1, IFERROR(VLOOKUP(A71&E71, '91_Data_ExRates'!A:D, 4, FALSE), 1)) -> 0
A72: 2024-05-03 | B72: Income | C72: OTP számla | D72: 80000 | E72: HUF | F72: Ösztöndíj | I72: Adam | K72: TX-1505 | L72: =D72*N72 -> 0 | N72: =IF(E72="HUF", 1, IFERROR(VLOOKUP(A72&E72, '91_Data_ExRates'!A:D, 4, FALSE), 1)) -> 0
A73: 2024-05-07 | B73: Expense | C73: OTP számla | D73: 330 | E73: HUF | F73: Étel-ital | I73: Adam | J73: Bueno automata Corvo | K73: TX-1396 | L73: =D73*N73 -> 0 | N73: =IF(E73="HUF", 1, IFERROR(VLOOKUP(A73&E73, '91_Data_ExRates'!A:D, 4, FALSE), 1)) -> 0
A74: 2024-05-08 | B74: Expense | C74: Készpénz | D74: 1600 | E74: HUF | F74: Luxus, szórakozás | I74: Adam | J74: Három oli 2 korsó Dreher | K74: TX-1395 | L74: =D74*N74 -> 0 | N74: =IF(E74="HUF", 1, IFERROR(VLOOKUP(A74&E74, '91_Data_ExRates'!A:D, 4, FALSE), 1)) -> 0
A75: 2024-05-11 | B75: Expense | C75: Készpénz | D75: 2000 | E75: HUF | F75: Ajándék | I75: Adam | J75: Tig öregdiák sportnap | K75: TX-1392 | L75: =D75*N75 -> 0 | N75: =IF(E75="HUF", 1, IFERROR(VLOOKUP(A75&E75, '91_Data_ExRates'!A:D, 4, FALSE), 1)) -> 0
A76: 2024-05-11 | B76: Expense | C76: Készpénz | D76: 1900 | E76: HUF | F76: Étel-ital | I76: Adam | J76: Kissarkany | K76: TX-1393 | L76: =D76*N76 -> 0 | N76: =IF(E76="HUF", 1, IFERROR(VLOOKUP(A76&E76, '91_Data_ExRates'!A:D, 4, FALSE), 1)) -> 0
A77: 2024-05-11 | B77: Expense | C77: Készpénz | D77: 720 | E77: HUF | F77: Étel-ital | I77: Adam | J77: Zacskos leves muller | K77: TX-1394 | L77: =D77*N77 -> 0 | N77: =IF(E77="HUF", 1, IFERROR(VLOOKUP(A77&E77, '91_Data_ExRates'!A:D, 4, FALSE), 1)) -> 0
A78: 2024-05-11 | B78: Expense | C78: Készpénz | D78: 6000 | E78: HUF | F78: Luxus, szórakozás | I78: Adam | J78: Kupadöntő | K78: TX-1391 | L78: =D78*N78 -> 0 | N78: =IF(E78="HUF", 1, IFERROR(VLOOKUP(A78&E78, '91_Data_ExRates'!A:D, 4, FALSE), 1)) -> 0
A79: 2024-05-11 | B79: Expense | C79: Készpénz | D79: 6000 | E79: HUF | F79: Ajándék | I79: Adam | J79: Kupadöntő Timinek | K79: TX-1390 | L79: =D79*N79 -> 0 | N79: =IF(E79="HUF", 1, IFERROR(VLOOKUP(A79&E79, '91_Data_ExRates'!A:D, 4, FALSE), 1)) -> 0
A80: 2024-05-13 | B80: Expense | C80: OTP számla | D80: 8500 | E80: HUF | F80: Luxus, szórakozás | I80: Adam | J80: Fradi - Újpest meccsjegy | K80: TX-1389 | L80: =D80*N80 -> 0 | N80: =IF(E80="HUF", 1, IFERROR(VLOOKUP(A80&E80, '91_Data_ExRates'!A:D, 4, FALSE), 1)) -> 0
A81: 2024-05-15 | B81: Expense | C81: OTP számla | D81: 3100 | E81: HUF | F81: Luxus, szórakozás | I81: Adam | J81: Meccs pia 2x | K81: TX-1388 | L81: =D81*N81 -> 0 | N81: =IF(E81="HUF", 1, IFERROR(VLOOKUP(A81&E81, '91_Data_ExRates'!A:D, 4, FALSE), 1)) -> 0
A82: 2024-05-15 | B82: Expense | C82: OTP számla | D82: 3000 | E82: HUF | F82: Étel-ital | I82: Adam | J82: Mekdo meccs után | K82: TX-1387 | L82: =D82*N82 -> 0 | N82: =IF(E82="HUF", 1, IFERROR(VLOOKUP(A82&E82, '91_Data_ExRates'!A:D, 4, FALSE), 1)) -> 0
A83: 2024-05-17 | B83: Income | C83: OTP számla | D83: 11900 | E83: HUF | F83: Üzletelés | I83: Adam | J83: MU mez | K83: TX-1504 | L83: =D83*N83 -> 0 | N83: =IF(E83="HUF", 1, IFERROR(VLOOKUP(A83&E83, '91_Data_ExRates'!A:D, 4, FALSE), 1)) -> 0
A84: 2024-05-19 | B84: Expense | C84: OTP számla | D84: 1300 | E84: HUF | F84: Luxus, szórakozás | I84: Adam | J84: Derbi fradikártya | K84: TX-1386 | L84: =D84*N84 -> 0 | N84: =IF(E84="HUF", 1, IFERROR(VLOOKUP(A84&E84, '91_Data_ExRates'!A:D, 4, FALSE), 1)) -> 0
... A93: 2024-06-04 | B93: Expense | C93: OTP számla | D93: 220 | E93: HUF | F93: Közlekedés | I93: Adam | J93: GDL buszjegy | K93: TX-1379 | L93: =D93*N93 -> 0 | N93: =IF(E93="HUF", 1, IFERROR(VLOOKUP(A93&E93, '91_Data_ExRates'!A:D, 4, FALSE), 1)) -> 0
A94: 2024-06-05 | B94: Income | C94: OTP számla | D94: 80000 | E94: HUF | F94: Ösztöndíj | I94: Adam | K94: TX-1501 | L94: =D94*N94 -> 0 | N94: =IF(E94="HUF", 1, IFERROR(VLOOKUP(A94&E94, '91_Data_ExRates'!A:D, 4, FALSE), 1)) -> 0
A95: 2024-06-06 | B95: Income | C95: Készpénz | D95: 20000 | E95: HUF | F95: Egyéb | I95: Adam | J95: Úszó bérletre | K95: TX-1500 | L95: =D95*N95 -> 0 | N95: =IF(E95="HUF", 1, IFERROR(VLOOKUP(A95&E95, '91_Data_ExRates'!A:D, 4, FALSE), 1)) -> 0
A96: 2024-06-06 | B96: Expense | C96: Készpénz | D96: 12900 | E96: HUF | F96: Fejlődés, befektetés | I96: Adam | J96: Úszóbérlet | K96: TX-1378 | L96: =D96*N96 -> 0 | N96: =IF(E96="HUF", 1, IFERROR(VLOOKUP(A96&E96, '91_Data_ExRates'!A:D, 4, FALSE), 1)) -> 0
A97: 2024-06-07 | B97: Expense | C97: Készpénz | D97: 700 | E97: HUF | F97: Luxus, szórakozás | I97: Adam | J97: Robinson meggyes soproni | K97: TX-1375 | L97: =D97*N97 -> 0 | N97: =IF(E97="HUF", 1, IFERROR(VLOOKUP(A97&E97, '91_Data_ExRates'!A:D, 4, FALSE), 1)) -> 0
A98: 2024-06-07 | B98: Expense | C98: Készpénz | D98: 1400 | E98: HUF | F98: Luxus, szórakozás | I98: Adam | J98: Fan vodka sprite | K98: TX-1377 | L98: =D98*N98 -> 0 | N98: =IF(E98="HUF", 1, IFERROR(VLOOKUP(A98&E98, '91_Data_ExRates'!A:D, 4, FALSE), 1)) -> 0
A99: 2024-06-07 | B99: Expense | C99: Készpénz | D99: 500 | E99: HUF | F99: Luxus, szórakozás | I99: Adam | J99: Bagoly kola 💀💀 | K99: TX-1374 | L99: =D99*N99 -> 0 | N99: =IF(E99="HUF", 1, IFERROR(VLOOKUP(A99&E99, '91_Data_ExRates'!A:D, 4, FALSE), 1)) -> 0
A100: 2024-06-07 | B100: Expense | C100: Készpénz | D100: 800 | E100: HUF | F100: Luxus, szórakozás | I100: Adam | J100: Fan stella (4dl) | K100: TX-1376 | L100: =D100*N100 -> 0 | N100: =IF(E100="HUF", 1, IFERROR(VLOOKUP(A100&E100, '91_Data_ExRates'!A:D, 4, FALSE), 1)) -> 0
A101: 2024-06-09 | B101: Expense | C101: OTP számla | D101: 45876 | E101: HUF | F101: Közlekedés | I101: Adam | J101: Burgasz szállás | K101: TX-1373 | L101: =D101*N101 -> 0 | N101: =IF(E101="HUF", 1, IFERROR(VLOOKUP(A101&E101, '91_Data_ExRates'!A:D, 4, FALSE), 1)) -> 0
A102: 2024-06-12 | B102: Expense | C102: Készpénz | D102: 3000 | E102: HUF | F102: Egyéb | I102: Adam | J102: Timi krém (utalta) | K102: TX-1372 | L102: =D102*N102 -> 0 | N102: =IF(E102="HUF", 1, IFERROR(VLOOKUP(A102&E102, '91_Data_ExRates'!A:D, 4, FALSE), 1)) -> 0
A103: 2024-06-12 | B103: Expense | C103: Készpénz | D103: 1400 | E103: HUF | F103: Ajándék | I103: Adam | J103: Timi harisnya | K103: TX-1371 | L103: =D103*N103 -> 0 | N103: =IF(E103="HUF", 1, IFERROR(VLOOKUP(A103&E103, '91_Data_ExRates'!A:D, 4, FALSE), 1)) -> 0
A104: 2024-06-12 | B104: Expense | C104: OTP számla | D104: 220 | E104: HUF | F104: Közlekedés | I104: Adam | J104: GDL jegy | K104: TX-1369 | L104: =D104*N104 -> 0 | N104: =IF(E104="HUF", 1, IFERROR(VLOOKUP(A104&E104, '91_Data_ExRates'!A:D, 4, FALSE), 1)) -> 0
A105: 2024-06-12 | B105: Expense | C105: OTP számla | D105: 220 | E105: HUF | F105: Közlekedés | I105: Adam | J105: GDL jegy | K105: TX-1370 | L105: =D105*N105 -> 0 | N105: =IF(E105="HUF", 1, IFERROR(VLOOKUP(A105&E105, '91_Data_ExRates'!A:D, 4, FALSE), 1)) -> 0
A106: 2024-06-12 | B106: Income | C106: OTP számla | D106: 3000 | E106: HUF | F106: Egyéb | I106: Adam | J106: Timi krém utalás | K106: TX-1499 | L106: =D106*N106 -> 0 | N106: =IF(E106="HUF", 1, IFERROR(VLOOKUP(A106&E106, '91_Data_ExRates'!A:D, 4, FALSE), 1)) -> 0
... A124: 2024-07-01 | B124: Expense | C124: Valuták (EUR) | D124: 1.46 | E124: EUR | F124: Egyéb | I124: Adam | J124: Váltás költsége | K124: TX-1356 | L124: =D124*N124 -> 0 | N124: =IF(E124="HUF", 1, IFERROR(VLOOKUP(A124&E124, '91_Data_ExRates'!A:D, 4, FALSE), 1)) -> 0
A125: 2024-07-01 | B125: Transfer | C125: Készpénz | D125: 60000 | E125: HUF | I125: Adam | J125: HUF-EUR váltás Arany change (395) | K125: TX-1547 | L125: =D125*N125 -> 0 | N125: =IF(E125="HUF", 1, IFERROR(VLOOKUP(A125&E125, '91_Data_ExRates'!A:D, 4, FALSE), 1)) -> 0
A126: 2024-07-01 | B126: Income | C126: Készpénz | D126: 30000 | E126: HUF | F126: Egyéb | I126: Adam | J126: Timitől Leva pénz | K126: TX-1493 | L126: =D126*N126 -> 0 | N126: =IF(E126="HUF", 1, IFERROR(VLOOKUP(A126&E126, '91_Data_ExRates'!A:D, 4, FALSE), 1)) -> 0
A127: 2024-07-02 | B127: Transfer | C127: Laptop kaució | D127: 50000 | E127: HUF | I127: Adam | K127: TX-1546 | L127: =D127*N127 -> 0 | N127: =IF(E127="HUF", 1, IFERROR(VLOOKUP(A127&E127, '91_Data_ExRates'!A:D, 4, FALSE), 1)) -> 0
A128: 2024-07-02 | B128: Income | C128: OTP számla | D128: 36100 | E128: HUF | F128: Egyéb | I128: Adam | J128: Timi: szállás, krúbi, cigi | K128: TX-1492 | L128: =D128*N128 -> 0 | N128: =IF(E128="HUF", 1, IFERROR(VLOOKUP(A128&E128, '91_Data_ExRates'!A:D, 4, FALSE), 1)) -> 0
A129: 2024-07-03 | B129: Expense | C129: Készpénz | D129: 3540 | E129: HUF | F129: Egészség | I129: Adam | J129: Gyógykrém shit | K129: TX-1355 | L129: =D129*N129 -> 0 | N129: =IF(E129="HUF", 1, IFERROR(VLOOKUP(A129&E129, '91_Data_ExRates'!A:D, 4, FALSE), 1)) -> 0
A130: 2024-07-03 | B130: Expense | C130: OTP számla | D130: 3990 | E130: HUF | F130: Egészség | I130: Adam | J130: Biztosítás Burgasz | K130: TX-1354 | L130: =D130*N130 -> 0 | N130: =IF(E130="HUF", 1, IFERROR(VLOOKUP(A130&E130, '91_Data_ExRates'!A:D, 4, FALSE), 1)) -> 0
A131: 2024-07-06 | B131: Expense | C131: OTP számla | D131: 8641 | E131: HUF | F131: Ajándék | I131: Adam | J131: Timi AC Milan mez | K131: TX-1353 | L131: =D131*N131 -> 0 | N131: =IF(E131="HUF", 1, IFERROR(VLOOKUP(A131&E131, '91_Data_ExRates'!A:D, 4, FALSE), 1)) -> 0
A132: 2024-07-07 | B132: Income | C132: Készpénz | D132: 20000 | E132: HUF | F132: Ajándék | I132: Adam | J132: Mama Burgasz költőpénz | K132: TX-1491 | L132: =D132*N132 -> 0 | N132: =IF(E132="HUF", 1, IFERROR(VLOOKUP(A132&E132, '91_Data_ExRates'!A:D, 4, FALSE), 1)) -> 0
A133: 2024-07-08 | B133: Expense | C133: Valuták (BGN) | D133: 4.5 | E133: BGN | F133: Étel-ital | I133: Adam | J133: Fagyi beannek | K133: TX-1347 | L133: =D133*N133 -> 0 | N133: =IF(E133="HUF", 1, IFERROR(VLOOKUP(A133&E133, '91_Data_ExRates'!A:D, 4, FALSE), 1)) -> 0
A134: 2024-07-08 | B134: Expense | C134: Valuták (BGN) | D134: 27.1 | E134: BGN | F134: Étel-ital | I134: Adam | J134: Yav-ka pizzák rendelés | K134: TX-1348 | L134: =D134*N134 -> 0 | N134: =IF(E134="HUF", 1, IFERROR(VLOOKUP(A134&E134, '91_Data_ExRates'!A:D, 4, FALSE), 1)) -> 0
...

Sheet 02_Accounts
A1: Name | B1: Type | C1: Currency | D1: Owner | E1: OpeningBalance | F1: IsArchived | G1: _MongoID 🔒
A2: Készpénz | B2: Bank | C2: HUF | D2: Adam | E2: 869500 | F2: FALSE | G2: 6a04c8576297c4682dd5cacc
A3: OTP számla | B3: Bank | C3: HUF | D3: Adam | E3: 325521.18 | F3: FALSE | G3: 6a04c8576297c4682dd5cacf
A4: Revolut Pro | B4: Bank | C4: HUF | D4: Adam | E4: 0 | F4: FALSE | G4: 6a04c8586297c4682dd5cad4
A5: Valuták (EUR) | B5: Bank | C5: EUR | D5: Adam | E5: 14.81 | F5: FALSE | G5: 6a04c8636297c4682dd5cbb2
A6: PayPal | B6: Bank | C6: HUF | D6: Adam | E6: 8737 | F6: FALSE | G6: 6a04c8666297c4682dd5cbf2
A7: Valuták (BGN) | B7: Bank | C7: BGN | D7: Adam | E7: 4.3 | F7: FALSE | G7: 6a04c8686297c4682dd5cc24
A8: Nexo | B8: Bank | C8: EUR | D8: Adam | E8: -251.49 | F8: FALSE | G8: 6a04c8716297c4682dd5ccbf
A9: Ajándékutalvány | B9: Bank | C9: HUF | D9: Adam | E9: 0 | F9: FALSE | G9: 6a04c8726297c4682dd5cce4
A10: Államkincstár | B10: Bank | C10: HUF | D10: Adam | E10: 1350000 | F10: FALSE | G10: 6a04c8726297c4682dd5cce6
A11: Wise | B11: Bank | C11: USD | D11: Adam | E11: -10.86 | F11: FALSE | G11: 6a04c8736297c4682dd5ccee
A12: Lightyear TBSZ | B12: Bank | C12: HUF | D12: Adam | E12: 0 | F12: FALSE | G12: 6a04c8736297c4682dd5ccf3
A13: Dapper wallet | B13: Bank | C13: USD | D13: Adam | E13: 521.22 | F13: FALSE | G13: 6a04c8746297c4682dd5cd05
A14: Laptop kaució | B14: Bank | C14: HUF | D14: Adam | E14: 0 | F14: FALSE | G14: 6a04c8746297c4682dd5cd0a

Sheet 03_BudgetsGoals
A1: Name | B1: Type | C1: Owner | D1: Target | E1: Period | F1: Note | G1: Deadline
A2: Élelmiszer | B2: Budget | C2: Adam | D2: 0 | E2: Monthly
A3: Szórakozás | B3: Budget | C3: Adam | D3: 0 | E3: Monthly
A4: Vésztartalék | B4: Goal | C4: Adam | D4: 0

Sheet 04_Pockets
A1: Pocket | B1: Owner | C1: Currency | D1: Target | E1: _MongoID 🔒
A2: Bari 2026 | B2: Adam | C2: HUF | D2: 200000 | E2: 6a05bfb43fc100a238d0b0df
A3: Vésztartalék | B3: Adam | C3: HUF | D3: 400000 | E3: 6a05c55603740ac92d5c4e54
A4: Hosszútávú | B4: Adam | C4: HUF | D4: 2000000 | E4: 6a05c5b803740ac92d5c4e56

Sheet 90_Settings
A1: People | B1: Categories | C1: Merchants | D1: Tags
A2: Adam | B2: Étel-ital | C2: Lidl | D2: Nyaralás
B3: Utazás | C3: Netflix | D3: Munka
B4: VitaSteps | C4: Spotify | D4: Ajándék
B5: Luxus, szórakozás | C5: Amazon
B6: Közlekedés
B7: Fejlődés, befektetés
B8: Egészség
B9: Egyéb
B10: Business befektetés
B11: Fizetés
B12: Ajándék
B13: Kamat
B14: Ösztöndíj
B15: Üzletelés

Sheet 91_Data_ExRates
A1: LookupKey 🔒 | B1: Date | C1: Currency | D1: Rate_to_HUF
A2: 2026-05-13AUD | B2: 2026-05-13 | C2: AUD | D2: 221.9953
A3: 2026-05-13BRL | B3: 2026-05-13 | C3: BRL | D3: 62.437988
A4: 2026-05-13CAD | B4: 2026-05-13 | C4: CAD | D4: 223.64237
A5: 2026-05-13CHF | B5: 2026-05-13 | C5: CHF | D5: 391.80775
A6: 2026-05-13CNY | B6: 2026-05-13 | C6: CNY | D6: 45.087737
A7: 2026-05-13CZK | B7: 2026-05-13 | C7: CZK | D7: 14.732821
A8: 2026-05-13DKK | B8: 2026-05-13 | C8: DKK | D8: 47.994327
A9: 2026-05-13GBP | B9: 2026-05-13 | C9: GBP | D9: 413.66346
A10: 2026-05-13HKD | B10: 2026-05-13 | C10: HKD | D10: 39.101761
A11: 2026-05-13IDR | B11: 2026-05-13 | C11: IDR | D11: 0.0175
A12: 2026-05-13ILS | B12: 2026-05-13 | C12: ILS | D12: 105.2956
A13: 2026-05-13INR | B13: 2026-05-13 | C13: INR | D13: 3.200413
... A5669: 2026-07-25ZWL | B5669: 2026-07-25 | C5669: ZWL | D5669: 11.926791

Sheet 91_Data_IDMap
A1: Sheet | B1: Name | C1: MongoID
A2: 02_Accounts | B2: Készpénz | C2: 6a04c8576297c4682dd5cacc
A3: 02_Accounts | B3: OTP számla | C3: 6a04c8576297c4682dd5cacf
A4: 02_Accounts | B4: Revolut Pro | C4: 6a04c8586297c4682dd5cad4
A5: 02_Accounts | B5: Valuták (EUR) | C5: 6a04c8636297c4682dd5cbb2
A6: 02_Accounts | B6: PayPal | C6: 6a04c8666297c4682dd5cbf2
A7: 02_Accounts | B7: Valuták (BGN) | C7: 6a04c8686297c4682dd5cc24
A8: 02_Accounts | B8: Nexo | C8: 6a04c8716297c4682dd5ccbf
A9: 02_Accounts | B9: Ajándékutalvány | C9: 6a04c8726297c4682dd5cce4
A10: 02_Accounts | B10: Államkincstár | C10: 6a04c8726297c4682dd5cce6
A11: 02_Accounts | B11: Wise | C11: 6a04c8736297c4682dd5ccee
A12: 02_Accounts | B12: Lightyear TBSZ | C12: 6a04c8736297c4682dd5ccf3
... A14: 02_Accounts | B14: Laptop kaució | C14: 6a04c8746297c4682dd5cd0a
